README.md
setup.py
flask_carbon_statsd/CarbonStatsd.py
flask_carbon_statsd/__init__.py
flask_carbon_statsd/flask_carbon_statsd.py
flask_carbon_statsd/metric_base.py
flask_carbon_statsd.egg-info/PKG-INFO
flask_carbon_statsd.egg-info/SOURCES.txt
flask_carbon_statsd.egg-info/dependency_links.txt
flask_carbon_statsd.egg-info/not-zip-safe
flask_carbon_statsd.egg-info/top_level.txt