Metadata-Version: 2.1
Name: flask-carbon-statsd
Version: 0.1
Summary: Flask metrics in Carbon Statsd format.
Home-page: https://github.com/labeneator/flask_carbon_statsd.git
Author: lmwangi
Author-email: lmwangi@gmail.com
License: BSD
Platform: any
Classifier: Environment :: Web Environment
Classifier: Intended Audience :: Developers
Classifier: License :: OSI Approved :: BSD License
Classifier: Operating System :: OS Independent
Classifier: Programming Language :: Python
Classifier: Topic :: Internet :: WWW/HTTP :: Dynamic Content
Classifier: Topic :: Software Development :: Libraries :: Python Modules
